priorityprefix.py
priorityprefix-1.3.2.dist-info/METADATA
priorityprefix-1.3.2.dist-info/WHEEL
priorityprefix-1.3.2.dist-info/top_level.txt
priorityprefix-1.3.2.dist-info/RECORD
