Metadata-Version: 2.1
Name: priorityprefix
Version: 1.3.2
Summary: Logging formatter to tell Journald's streams the correct severity level
Home-page: https://github.com/pscl4rke/priorityprefix
Author: P. S. Clarke
Author-email: priorityprefix@pscl4rke.net
License: cf:licence
Project-URL: Source Code, https://github.com/pscl4rke/priorityprefix
Project-URL: Issues, https://github.com/pscl4rke/priorityprefix/issues
Project-URL: Licence, https://github.com/pscl4rke/priorityprefix/blob/master/LICENCE.txt
Classifier: Development Status :: 5 - Production/Stable
Classifier: Environment :: No Input/Output (Daemon)
Classifier: Programming Language :: Python :: 3.6
Classifier: Programming Language :: Python :: 3.7
Classifier: Programming Language :: Python :: 3.8
Classifier: Programming Language :: Python :: 3.9
Classifier: Programming Language :: Python :: 3.10
Classifier: Programming Language :: Python :: 3.11
Classifier: Programming Language :: Python :: 3.12
Classifier: Programming Language :: Python :: 3.13
Classifier: Topic :: System :: Logging
Requires-Python: >=3.6
